hackgen/__init__.py
hackgen/language.py
hackgen/test_generator.py
hackgen/test_input_format.py
hackgen-1.0.1.dist-info/METADATA
hackgen-1.0.1.dist-info/RECORD
hackgen-1.0.1.dist-info/WHEEL
hackgen-1.0.1.dist-info/top_level.txt
