Metadata-Version: 2.1
Name: hackgen
Version: 1.0.1
Summary: HackerRank Test-Case Generator
Home-page: https://github.com/renuka-fernando/hackgen
Author: Renuka Fernando
Author-email: renukapiyumal@gmail.com
License: MIT
Platform: UNKNOWN
Classifier: Programming Language :: Python :: 3
Classifier: Operating System :: OS Independent
